Metadata-Version: 2.1
Name: gregetsuro-dist
Version: 0.1
Summary: Gaussian distributions
Author: Greg Montana
Author-email: gregorymontana@gmail.com
